uberlogs/__init__.py
uberlogs/level.py
uberlogs/private.py
uberlogs/public.py
uberlogs/formatters/__init__.py
uberlogs/formatters/base.py
uberlogs/formatters/concatf.py
uberlogs/formatters/jsonf.py
uberlogs/formatters/simple_jsonf.py
uberlogs/handlers/__init__.py
uberlogs/handlers/kill_process.py
uberlogs-0.0.6.dist-info/DESCRIPTION.rst
uberlogs-0.0.6.dist-info/LICENSE.txt
uberlogs-0.0.6.dist-info/METADATA
uberlogs-0.0.6.dist-info/RECORD
uberlogs-0.0.6.dist-info/WHEEL
uberlogs-0.0.6.dist-info/metadata.json
uberlogs-0.0.6.dist-info/top_level.txt
