Metadata-Version: 2.0
Name: uberlogs
Version: 0.0.6
Summary: UberLogs
Home-page: http://github.com/odedlaz/uberlogs
Author: Oded Lazar
Author-email: odedlaz@gmail.com
License: MIT License
Platform: any
Classifier: Development Status :: 5 - Production/Stable
Classifier: Natural Language :: English
Classifier: Intended Audience :: Developers
Classifier: Operating System :: OS Independent
Classifier: License :: OSI Approved :: MIT License
Classifier: Programming Language :: Python
Classifier: Programming Language :: Python :: 2
Classifier: Programming Language :: Python :: 2.6
Classifier: Programming Language :: Python :: 2.7
Classifier: Programming Language :: Python :: 3
Classifier: Programming Language :: Python :: 3.3
Classifier: Programming Language :: Python :: 3.4
Classifier: Programming Language :: Python :: 3.5
Classifier: Topic :: Software Development :: Libraries :: Python Modules
Classifier: Topic :: Software Development :: Libraries :: Application Frameworks
Requires-Dist: ujson
Requires-Dist: six
Requires-Dist: pytz
Provides-Extra: testing
Requires-Dist: pytest; extra == 'testing'
